{
    "created_at": "Sat Apr 25 13:58:27 +0000 2020",
    "id": 1254047122363609094,
    "id_str": "1254047122363609094",
    "text": "हर शनिवार ‘काला’ नहीं होता ! कोरोना पर उत्तराखंड के लिए आई अच्छी ख़बर https://t.co/0i3oe7GuWD via @uttarakhandpost",
    "source": "<a href=\"http://twitter.com\" rel=\"nofollow\">Twitter Web Client</a>",
    "truncated": false,
    "in_reply_to_status_id": null,
    "in_reply_to_status_id_str": null,
    "in_reply_to_user_id": null,
    "in_reply_to_user_id_str": null,
    "in_reply_to_screen_name": null,
    "user": {
        "id": 2495044472,
        "id_str": "2495044472",
        "name": "Uttarakhand Post",
        "screen_name": "uttarakhandpost",
        "location": "Uttarakhand",
        "url": "http://www.uttarakhandpost.com",
        "description": "Focused on #Uttarakhand, News from the World. Subcribe on Youtube- http://www.youtube.com/c/UttarakhandPost",
        "translator_type": "none",
        "protected": false,
        "verified": false,
        "followers_count": 7561,
        "friends_count": 51,
        "listed_count": 46,
        "favourites_count": 1659,
        "statuses_count": 76240,
        "created_at": "Wed May 14 21:33:29 +0000 2014",
        "utc_offset": null,
        "time_zone": null,
        "geo_enabled": true,
        "lang": null,
        "contributors_enabled": false,
        "is_translator": false,
        "profile_background_color": "000000",
        "profile_background_image_url": "http://abs.twimg.com/images/themes/theme15/bg.png",
        "profile_background_image_url_https": "https://abs.twimg.com/images/themes/theme15/bg.png",
        "profile_background_tile": false,
        "profile_link_color": "1B95E0",
        "profile_sidebar_border_color": "000000",
        "profile_sidebar_fill_color": "000000",
        "profile_text_color": "000000",
        "profile_use_background_image": false,
        "profile_image_url": "http://pbs.twimg.com/profile_images/932905910862626817/_0CvLDjq_normal.jpg",
        "profile_image_url_https": "https://pbs.twimg.com/profile_images/932905910862626817/_0CvLDjq_normal.jpg",
        "profile_banner_url": "https://pbs.twimg.com/profile_banners/2495044472/1585068904",
        "default_profile": false,
        "default_profile_image": false,
        "following": null,
        "follow_request_sent": null,
        "notifications": null
    },
    "geo": null,
    "coordinates": null,
    "place": null,
    "contributors": null,
    "is_quote_status": false,
    "quote_count": 0,
    "reply_count": 0,
    "retweet_count": 0,
    "favorite_count": 0,
    "entities": {
        "hashtags": [],
        "urls": [
            {
                "url": "https://t.co/0i3oe7GuWD",
                "expanded_url": "http://uttarakhandpost.com/good-news-for-uttarakhand-on-corona-2/",
                "display_url": "uttarakhandpost.com/good-news-for-…",
                "indices": [
                    70,
                    93
                ]
            }
        ],
        "user_mentions": [
            {
                "screen_name": "uttarakhandpost",
                "name": "Uttarakhand Post",
                "id": 2495044472,
                "id_str": "2495044472",
                "indices": [
                    98,
                    114
                ]
            }
        ],
        "symbols": []
    },
    "favorited": false,
    "retweeted": false,
    "possibly_sensitive": false,
    "filter_level": "low",
    "lang": "hi",
    "timestamp_ms": "1587823107697"
}