{
    "created_at": "Sat Apr 25 12:39:25 +0000 2020",
    "id": 1254027230751141889,
    "id_str": "1254027230751141889",
    "text": "@Corsnor1982 @Wiep13396680 @telegraaf @BLIKOPENER3331 @ALidwien Hoef ik geen paniek voor te zaaien. Iedereen binnen… https://t.co/PrLerdu2IF",
    "display_text_range": [
        64,
        140
    ],
    "source": "<a href=\"https://mobile.twitter.com\" rel=\"nofollow\">Twitter Web App</a>",
    "truncated": true,
    "in_reply_to_status_id": 1253991990418702336,
    "in_reply_to_status_id_str": "1253991990418702336",
    "in_reply_to_user_id": 1239132445527683074,
    "in_reply_to_user_id_str": "1239132445527683074",
    "in_reply_to_screen_name": "Corsnor1982",
    "user": {
        "id": 1228978741688270850,
        "id_str": "1228978741688270850",
        "name": "Mad Marty",
        "screen_name": "MadMarty3",
        "location": "Ravels",
        "url": "https://madmartys.blogspot.com/",
        "description": "Argumenteer nooit met een gek\nHij neemt u mee naar zijn niveau\nen verslaat u op basis van ervaring \n\nVolgen op eigen risico!",
        "translator_type": "none",
        "protected": false,
        "verified": false,
        "followers_count": 176,
        "friends_count": 192,
        "listed_count": 0,
        "favourites_count": 1294,
        "statuses_count": 4578,
        "created_at": "Sun Feb 16 09:45:56 +0000 2020",
        "utc_offset": null,
        "time_zone": null,
        "geo_enabled": false,
        "lang": null,
        "contributors_enabled": false,
        "is_translator": false,
        "profile_background_color": "F5F8FA",
        "profile_background_image_url": "",
        "profile_background_image_url_https": "",
        "profile_background_tile": false,
        "profile_link_color": "1DA1F2",
        "profile_sidebar_border_color": "C0DEED",
        "profile_sidebar_fill_color": "DDEEF6",
        "profile_text_color": "333333",
        "profile_use_background_image": true,
        "profile_image_url": "http://pbs.twimg.com/profile_images/1228978954477936640/06i7ykv3_normal.png",
        "profile_image_url_https": "https://pbs.twimg.com/profile_images/1228978954477936640/06i7ykv3_normal.png",
        "profile_banner_url": "https://pbs.twimg.com/profile_banners/1228978741688270850/1582441182",
        "default_profile": true,
        "default_profile_image": false,
        "following": null,
        "follow_request_sent": null,
        "notifications": null
    },
    "geo": null,
    "coordinates": null,
    "place": null,
    "contributors": null,
    "is_quote_status": false,
    "extended_tweet": {
        "full_text": "@Corsnor1982 @Wiep13396680 @telegraaf @BLIKOPENER3331 @ALidwien Hoef ik geen paniek voor te zaaien. Iedereen binnen de risicogroep gaat eraan als hij corona krijgt. Op een uitzondering na.",
        "display_text_range": [
            64,
            188
        ],
        "entities": {
            "hashtags": [],
            "urls": [],
            "user_mentions": [
                {
                    "screen_name": "Corsnor1982",
                    "name": "Cor",
                    "id": 1239132445527683074,
                    "id_str": "1239132445527683074",
                    "indices": [
                        0,
                        12
                    ]
                },
                {
                    "screen_name": "Wiep13396680",
                    "name": "Wiep🚛🎼🎶 ook te vinden op gab.com/jagerrmeister",
                    "id": 1132634614470729734,
                    "id_str": "1132634614470729734",
                    "indices": [
                        13,
                        26
                    ]
                },
                {
                    "screen_name": "telegraaf",
                    "name": "De Telegraaf",
                    "id": 2902821,
                    "id_str": "2902821",
                    "indices": [
                        27,
                        37
                    ]
                },
                {
                    "screen_name": "BLIKOPENER3331",
                    "name": "@BLIKOPENER333",
                    "id": 1180862242763489287,
                    "id_str": "1180862242763489287",
                    "indices": [
                        38,
                        53
                    ]
                },
                {
                    "screen_name": "ALidwien",
                    "name": "ARCHIEF333LIDWIEN",
                    "id": 1247329228632330241,
                    "id_str": "1247329228632330241",
                    "indices": [
                        54,
                        63
                    ]
                }
            ],
            "symbols": []
        }
    },
    "quote_count": 0,
    "reply_count": 0,
    "retweet_count": 0,
    "favorite_count": 0,
    "entities": {
        "hashtags": [],
        "urls": [
            {
                "url": "https://t.co/PrLerdu2IF",
                "expanded_url": "https://twitter.com/i/web/status/1254027230751141889",
                "display_url": "twitter.com/i/web/status/1…",
                "indices": [
                    117,
                    140
                ]
            }
        ],
        "user_mentions": [
            {
                "screen_name": "Corsnor1982",
                "name": "Cor",
                "id": 1239132445527683074,
                "id_str": "1239132445527683074",
                "indices": [
                    0,
                    12
                ]
            },
            {
                "screen_name": "Wiep13396680",
                "name": "Wiep🚛🎼🎶 ook te vinden op gab.com/jagerrmeister",
                "id": 1132634614470729734,
                "id_str": "1132634614470729734",
                "indices": [
                    13,
                    26
                ]
            },
            {
                "screen_name": "telegraaf",
                "name": "De Telegraaf",
                "id": 2902821,
                "id_str": "2902821",
                "indices": [
                    27,
                    37
                ]
            },
            {
                "screen_name": "BLIKOPENER3331",
                "name": "@BLIKOPENER333",
                "id": 1180862242763489287,
                "id_str": "1180862242763489287",
                "indices": [
                    38,
                    53
                ]
            },
            {
                "screen_name": "ALidwien",
                "name": "ARCHIEF333LIDWIEN",
                "id": 1247329228632330241,
                "id_str": "1247329228632330241",
                "indices": [
                    54,
                    63
                ]
            }
        ],
        "symbols": []
    },
    "favorited": false,
    "retweeted": false,
    "filter_level": "low",
    "lang": "nl",
    "timestamp_ms": "1587818365167"
}