{
    "created_at": "Sat Apr 25 14:27:43 +0000 2020",
    "id": 1254054488815611904,
    "id_str": "1254054488815611904",
    "text": "🤣🤣 I was shocked to.. Give a speech about corona you talking abt something else",
    "source": "<a href=\"http://twitter.com/download/android\" rel=\"nofollow\">Twitter for Android</a>",
    "truncated": false,
    "in_reply_to_status_id": null,
    "in_reply_to_status_id_str": null,
    "in_reply_to_user_id": null,
    "in_reply_to_user_id_str": null,
    "in_reply_to_screen_name": null,
    "user": {
        "id": 1218174159454425088,
        "id_str": "1218174159454425088",
        "name": "/\\/\\|)🐍",
        "screen_name": "MiZtA_MD1",
        "location": null,
        "url": null,
        "description": "Your uncle|¶",
        "translator_type": "none",
        "protected": false,
        "verified": false,
        "followers_count": 2980,
        "friends_count": 150,
        "listed_count": 3,
        "favourites_count": 18080,
        "statuses_count": 23520,
        "created_at": "Fri Jan 17 14:12:20 +0000 2020",
        "utc_offset": null,
        "time_zone": null,
        "geo_enabled": false,
        "lang": null,
        "contributors_enabled": false,
        "is_translator": false,
        "profile_background_color": "F5F8FA",
        "profile_background_image_url": "",
        "profile_background_image_url_https": "",
        "profile_background_tile": false,
        "profile_link_color": "1DA1F2",
        "profile_sidebar_border_color": "C0DEED",
        "profile_sidebar_fill_color": "DDEEF6",
        "profile_text_color": "333333",
        "profile_use_background_image": true,
        "profile_image_url": "http://pbs.twimg.com/profile_images/1248999381728190464/KQOt7Gi8_normal.jpg",
        "profile_image_url_https": "https://pbs.twimg.com/profile_images/1248999381728190464/KQOt7Gi8_normal.jpg",
        "profile_banner_url": "https://pbs.twimg.com/profile_banners/1218174159454425088/1586673222",
        "default_profile": true,
        "default_profile_image": false,
        "following": null,
        "follow_request_sent": null,
        "notifications": null
    },
    "geo": null,
    "coordinates": null,
    "place": null,
    "contributors": null,
    "quoted_status_id": 1254043791956348929,
    "quoted_status_id_str": "1254043791956348929",
    "quoted_status": {
        "created_at": "Sat Apr 25 13:45:13 +0000 2020",
        "id": 1254043791956348929,
        "id_str": "1254043791956348929",
        "text": "Wetin concern gucci &amp; gabbana with Corona Virus? \n\nI’m not understanding",
        "source": "<a href=\"http://twitter.com/download/iphone\" rel=\"nofollow\">Twitter for iPhone</a>",
        "truncated": false,
        "in_reply_to_status_id": null,
        "in_reply_to_status_id_str": null,
        "in_reply_to_user_id": null,
        "in_reply_to_user_id_str": null,
        "in_reply_to_screen_name": null,
        "user": {
            "id": 3161136544,
            "id_str": "3161136544",
            "name": "LazyChef 👨‍🍳",
            "screen_name": "JahmalUsen",
            "location": "Lagos, Nigeria",
            "url": null,
            "description": "Lazy Chef | Talent Manager | ex blogger. Focused on Lifestyle, Entertainment and Enjoyment | Partner @Nestriad",
            "translator_type": "none",
            "protected": false,
            "verified": false,
            "followers_count": 31562,
            "friends_count": 19745,
            "listed_count": 250,
            "favourites_count": 112345,
            "statuses_count": 255018,
            "created_at": "Sun Apr 12 20:16:16 +0000 2015",
            "utc_offset": null,
            "time_zone": null,
            "geo_enabled": true,
            "lang": null,
            "contributors_enabled": false,
            "is_translator": false,
            "profile_background_color": "C0DEED",
            "profile_background_image_url": "http://abs.twimg.com/images/themes/theme1/bg.png",
            "profile_background_image_url_https": "https://abs.twimg.com/images/themes/theme1/bg.png",
            "profile_background_tile": false,
            "profile_link_color": "1DA1F2",
            "profile_sidebar_border_color": "C0DEED",
            "profile_sidebar_fill_color": "DDEEF6",
            "profile_text_color": "333333",
            "profile_use_background_image": true,
            "profile_image_url": "http://pbs.twimg.com/profile_images/1253050779386163201/5u0g2fbn_normal.jpg",
            "profile_image_url_https": "https://pbs.twimg.com/profile_images/1253050779386163201/5u0g2fbn_normal.jpg",
            "profile_banner_url": "https://pbs.twimg.com/profile_banners/3161136544/1584776215",
            "default_profile": true,
            "default_profile_image": false,
            "following": null,
            "follow_request_sent": null,
            "notifications": null
        },
        "geo": null,
        "coordinates": null,
        "place": null,
        "contributors": null,
        "is_quote_status": false,
        "quote_count": 0,
        "reply_count": 2,
        "retweet_count": 2,
        "favorite_count": 3,
        "entities": {
            "hashtags": [],
            "urls": [],
            "user_mentions": [],
            "symbols": []
        },
        "favorited": false,
        "retweeted": false,
        "filter_level": "low",
        "lang": "en"
    },
    "quoted_status_permalink": {
        "url": "https://t.co/ZWwm6jQtf1",
        "expanded": "https://twitter.com/JahmalUsen/status/1254043791956348929",
        "display": "twitter.com/JahmalUsen/sta…"
    },
    "is_quote_status": true,
    "quote_count": 0,
    "reply_count": 0,
    "retweet_count": 0,
    "favorite_count": 0,
    "entities": {
        "hashtags": [],
        "urls": [],
        "user_mentions": [],
        "symbols": []
    },
    "favorited": false,
    "retweeted": false,
    "filter_level": "low",
    "lang": "en",
    "timestamp_ms": "1587824863996"
}